{
  "body": "def token_budget(self) -> TokenBudget:\n    return self._conversation.budget\n",
  "body_hash": "efc67302f6533076",
  "body_truncated": false,
  "callers_of": [],
  "component_schema": "ASSADE-SPEC-003",
  "description": "Draft candidate from C:/!ass-ade-evoMERGE-g3-20260419-003649/a0_qk_constants/qk_draft_token_budget.py:7.",
  "exceptions_raised": [],
  "fulfills_blueprints": [],
  "id": "qk.source.a0_qk_constants.token_budget",
  "imports": [
    "__future__.annotations"
  ],
  "interfaces": {
    "source": "C:/!ass-ade-evoMERGE-g3-20260419-003649/a0_qk_constants/qk_draft_token_budget.py:7"
  },
  "kind": "invariant",
  "made_of": [],
  "name": "token_budget",
  "product_categories": [
    "COR"
  ],
  "provides": [
    "rebuild candidate for token_budget"
  ],
  "reuse_policy": "reference-only",
  "status": "draft",
  "tier": "a0_qk_constants",
  "version": "0.1.0"
}
