{
  "body": "def get_pricing_manifest(self) -> PricingManifest:\n    \"\"\"/.well-known/pricing.json \u2014 machine-readable tiers, free\"\"\"\n    return self._get_model(\"/.well-known/pricing.json\", PricingManifest)\n",
  "body_hash": "a9edbb9e544b970c",
  "body_truncated": false,
  "callers_of": [
    "_get_model"
  ],
  "component_schema": "ASSADE-SPEC-003",
  "description": "Draft candidate from C:/!ass-ade-evoMERGE-g3-20260419-003649/a0_qk_constants/qk_draft_get_pricing_manifest.py:7.",
  "exceptions_raised": [],
  "fulfills_blueprints": [],
  "id": "qk.source.a0_qk_constants.get_pricing_manifest",
  "imports": [
    "__future__.annotations"
  ],
  "interfaces": {
    "source": "C:/!ass-ade-evoMERGE-g3-20260419-003649/a0_qk_constants/qk_draft_get_pricing_manifest.py:7"
  },
  "kind": "invariant",
  "made_of": [],
  "name": "get_pricing_manifest",
  "product_categories": [
    "COR"
  ],
  "provides": [
    "rebuild candidate for get_pricing_manifest"
  ],
  "reuse_policy": "reference-only",
  "status": "draft",
  "tier": "a0_qk_constants",
  "version": "0.1.0"
}
