{
  "body": "def on_progress(name: str, status: StepStatus, current: int, total: int) -> None:\n    calls.append((name, status, current, total))\n",
  "body_hash": "631be6916fd22859",
  "body_truncated": false,
  "callers_of": [
    "append"
  ],
  "component_schema": "ASSADE-SPEC-003",
  "description": "Draft candidate from C:/!ass-ade-evoMERGE-g3-20260419-003649/a1_at_functions/at_draft_test_callback_is_called.py:10.",
  "exceptions_raised": [],
  "fulfills_blueprints": [],
  "id": "at.source.a1_at_functions.on_progress",
  "imports": [
    "__future__.annotations"
  ],
  "interfaces": {
    "source": "C:/!ass-ade-evoMERGE-g3-20260419-003649/a1_at_functions/at_draft_test_callback_is_called.py:10"
  },
  "kind": "pure_function",
  "made_of": [],
  "name": "on_progress",
  "product_categories": [
    "COR"
  ],
  "provides": [
    "rebuild candidate for on_progress"
  ],
  "reuse_policy": "reference-only",
  "status": "draft",
  "tier": "a1_at_functions",
  "version": "0.1.0"
}
