{
  "body": "class Principle:\n    text: str\n    weight: float\n    source_traces: int\n",
  "body_hash": "149c8a7dc4b21c9f",
  "body_truncated": false,
  "callers_of": [],
  "component_schema": "ASSADE-SPEC-003",
  "description": "Draft candidate from C:/!ass-ade-evoMERGE-g3-20260419-003649/a2_mo_composites/mo_draft_principle.py:7.",
  "exceptions_raised": [],
  "fulfills_blueprints": [],
  "id": "mo.source.a2_mo_composites.principle",
  "imports": [
    "__future__.annotations"
  ],
  "interfaces": {
    "source": "C:/!ass-ade-evoMERGE-g3-20260419-003649/a2_mo_composites/mo_draft_principle.py:7"
  },
  "kind": "engine_molecule",
  "made_of": [],
  "name": "Principle",
  "product_categories": [
    "COR"
  ],
  "provides": [
    "rebuild candidate for Principle"
  ],
  "reuse_policy": "reference-only",
  "status": "draft",
  "tier": "a2_mo_composites",
  "version": "0.1.0"
}
